data_structure.pypy37-pp73-x86_64-linux-gnu.so
UtilsRL/__init__.py
UtilsRL/logger/__init__.py
UtilsRL/logger/tensorboard_logger.py
UtilsRL/logger/csv_logger.py
UtilsRL/logger/composite_logger.py
UtilsRL/logger/wandb_logger.py
UtilsRL/logger/base_logger.py
UtilsRL/misc/__init__.py
UtilsRL/misc/chore.py
UtilsRL/misc/decorator.py
UtilsRL/misc/namespace.py
UtilsRL/rl/__init__.py
UtilsRL/rl/video_recorder.py
UtilsRL/rl/actor.py
UtilsRL/rl/critic.py
UtilsRL/rl/normalizer.py
UtilsRL/rl/buffer/__init__.py
UtilsRL/rl/buffer/transition_replay.py
UtilsRL/rl/buffer/base.py
UtilsRL/rl/buffer/prioritized_replay.py
UtilsRL/net/__init__.py
UtilsRL/net/rnn.py
UtilsRL/net/cnn.py
UtilsRL/net/basic.py
UtilsRL/net/mlp.py
UtilsRL/net/utils.py
UtilsRL/data_structure/__init__.py
UtilsRL/data_structure/data_structure.cc
UtilsRL/third_party/__init__.py
UtilsRL/third_party/tqdm.py
UtilsRL/math/__init__.py
UtilsRL/math/distributions.py
UtilsRL/env/__init__.py
UtilsRL/env/wrapper/dmc_wrapper.py
UtilsRL/env/wrapper/mujoco_wrapper.py
UtilsRL/env/wrapper/__init__.py
UtilsRL/env/wrapper/atari_wrapper.py
UtilsRL/env/wrapper/base_wrapper.py
UtilsRL/env/wrapper/compat.py
UtilsRL/exp/_device.py
UtilsRL/exp/__init__.py
UtilsRL/exp/argparse.py
UtilsRL/exp/_seed.py
UtilsRL/plot/__init__.py
UtilsRL/plot/tb_parser.py
UtilsRL-0.6.11.dist-info/LICENSE
UtilsRL-0.6.11.dist-info/WHEEL
UtilsRL-0.6.11.dist-info/top_level.txt
UtilsRL-0.6.11.dist-info/RECORD
UtilsRL-0.6.11.dist-info/METADATA
