Metadata-Version: 2.1
Name: UtilsRL
Version: 0.6.11
Summary: A python module desgined for RL logging, monitoring and experiments managing. 
Home-page: https://github.com/typoverflow/UtilsRL
Author: typoverflow
Author-email: typoverflow@outlook.com
License: MIT
Requires-Python: >=3.7
License-File: LICENSE
Requires-Dist: gym <=0.24.1,>=0.23.1
Requires-Dist: tqdm
Requires-Dist: numpy
Requires-Dist: torch
Requires-Dist: pandas
Requires-Dist: opencv-python
